dinamis_sdk/__init__.py
dinamis_sdk/cli.py
dinamis_sdk/http.py
dinamis_sdk/model.py
dinamis_sdk/oauth2.py
dinamis_sdk/py.typed
dinamis_sdk/settings.py
dinamis_sdk/signing.py
dinamis_sdk/upload.py
dinamis_sdk/utils.py
dinamis_sdk/examples/__init__.py
dinamis_sdk/examples/pyotb_ndvi_loss.py
dinamis_sdk/examples/pyotb_toa_mosaic.py
dinamis_sdk/examples/rio_metadata.py
dinamis_sdk-0.5.3.dist-info/licenses/LICENSE
dinamis_sdk-0.5.3.dist-info/METADATA
dinamis_sdk-0.5.3.dist-info/WHEEL
dinamis_sdk-0.5.3.dist-info/entry_points.txt
dinamis_sdk-0.5.3.dist-info/top_level.txt
dinamis_sdk-0.5.3.dist-info/RECORD
