Metadata-Version: 2.4
Name: dinamis-sdk
Version: 0.5.3
Summary: DINAMIS SDK for Python
Author-email: Rémi Cresson <remi.cresson@inrae.fr>, Pablo Boizeau <pablo.boizeau@ird.fr>
License:                                  Apache License
Requires-Python: >=3.7
License-File: LICENSE
Requires-Dist: setuptools>=61.2
Requires-Dist: click>=7.1
Requires-Dist: pydantic<3.0.0,>=1.7.3
Requires-Dist: pystac>=1.0.0
Requires-Dist: pystac-client>=0.2.0
Requires-Dist: requests>=2.25.1
Requires-Dist: packaging
Requires-Dist: qrcode
Requires-Dist: appdirs
Requires-Dist: pydantic_settings
Dynamic: license-file
